README.md
setup.py
qth_panasonic_viera/__init__.py
qth_panasonic_viera/version.py
qth_panasonic_viera.egg-info/PKG-INFO
qth_panasonic_viera.egg-info/SOURCES.txt
qth_panasonic_viera.egg-info/dependency_links.txt
qth_panasonic_viera.egg-info/entry_points.txt
qth_panasonic_viera.egg-info/requires.txt
qth_panasonic_viera.egg-info/top_level.txt